kosmoy_sdk/__init__.py
kosmoy_sdk/_kosmoy_base.py
kosmoy_sdk/client.py
kosmoy_sdk/environment.py
kosmoy_sdk/exceptions.py
kosmoy_sdk/models.py
kosmoy_sdk/langchain/__init__.py
kosmoy_sdk/langchain/client.py
kosmoy_sdk-0.1.7.dev0.dist-info/METADATA
kosmoy_sdk-0.1.7.dev0.dist-info/WHEEL
kosmoy_sdk-0.1.7.dev0.dist-info/top_level.txt
kosmoy_sdk-0.1.7.dev0.dist-info/RECORD
