Metadata-Version: 2.4
Name: kosmoy-sdk
Version: 0.1.7.dev0
Summary: A Gateway SDK for making API requests
Home-page: https://github.com/KosmoyAI/kosmoy-sdk
Author: Olsi Hoxha
Author-email: olsi.hoxha@kosmoy.com
Classifier: Programming Language :: Python :: 3
Classifier: License :: OSI Approved :: MIT License
Classifier: Operating System :: OS Independent
Requires-Python: >=3.7
Requires-Dist: pydantic>=2.11.5
Requires-Dist: requests>=2.32.3
Requires-Dist: openai>=1.82.1
Requires-Dist: h11>=0.16.0
Provides-Extra: langchain
Requires-Dist: langchain-openai==0.3.18; extra == "langchain"
Dynamic: author
Dynamic: author-email
Dynamic: classifier
Dynamic: description
Dynamic: description-content-type
Dynamic: home-page
Dynamic: provides-extra
Dynamic: requires-dist
Dynamic: requires-python
Dynamic: summary
